vise_delegator_core/__init__.py
vise_delegator_core/delegator.py
vise_delegator_core-0.2.0.dist-info/LICENSE
vise_delegator_core-0.2.0.dist-info/METADATA
vise_delegator_core-0.2.0.dist-info/WHEEL
vise_delegator_core-0.2.0.dist-info/entry_points.txt
vise_delegator_core-0.2.0.dist-info/top_level.txt
vise_delegator_core-0.2.0.dist-info/RECORD
